FreeProxyRevolver.py
FreeProxyRevolver-0.1.1.dist-info/LICENSE
FreeProxyRevolver-0.1.1.dist-info/METADATA
FreeProxyRevolver-0.1.1.dist-info/WHEEL
FreeProxyRevolver-0.1.1.dist-info/top_level.txt
FreeProxyRevolver-0.1.1.dist-info/RECORD
