Metadata-Version: 2.1
Name: FreeProxyRevolver
Version: 0.1.1
Summary: a package that allows you to automatically revolve your http requests through various proxies
Home-page: https://github.com/Themis3000/FreeProxyRevolver
Author: Themi Megas
Author-email: tcm4760@gmail.com
License: UNKNOWN
Platform: UNKNOWN
Classifier: Programming Language :: Python :: 3.7
Classifier: Programming Language :: Python :: 3.8
Classifier: Programming Language :: Python :: 3.9
Classifier: Programming Language :: Python :: 3.10
Classifier: License :: OSI Approved :: MIT License
Classifier: Operating System :: OS Independent
License-File: LICENSE
Requires-Dist: requests[socks]
Requires-Dist: FreeProxyScraper
Requires-Dist: fake-useragent
Provides-Extra: dev
Requires-Dist: pytest ; extra == 'dev'
